niceapp6/__init__.py
niceapp6/app.py
niceapp6/build.py
niceapp6-0.2.0.dist-info/METADATA
niceapp6-0.2.0.dist-info/WHEEL
niceapp6-0.2.0.dist-info/entry_points.txt
niceapp6-0.2.0.dist-info/RECORD
