Metadata-Version: 2.3
Name: niceapp6
Version: 0.2.0
Summary: Add your description here
Author-email: Masuda Shinsuke <shinsuke.masuda@gmail.com>
Requires-Python: >=3.8
Requires-Dist: nicegui>=1.4.18
Requires-Dist: pyinstaller>=6.5.0
Requires-Dist: pywebview>=5.0.5
